tests/__init__.py
tests/test_console.py
tests/test_log_time.py
tests/test_logs.py
loggingclient-0.0.5.dist-info/METADATA
loggingclient-0.0.5.dist-info/WHEEL
loggingclient-0.0.5.dist-info/top_level.txt
loggingclient-0.0.5.dist-info/RECORD
