Metadata-Version: 2.1
Name: loggingclient
Version: 0.0.5
Summary: A library to log to the console and other platforms.
License: UNKNOWN
Platform: UNKNOWN
Requires-Python: >=3.9
Requires-Dist: pylogctx (==1.12)
